MANIFEST.in
README.md
requirements.txt
setup.cfg
setup.py
versioneer.py
stancache/__init__.py
stancache/_version.py
stancache/config.py
stancache/defaults.py
stancache/seed.py
stancache/stancache.py
stancache/utils.py
stancache.egg-info/PKG-INFO
stancache.egg-info/SOURCES.txt
stancache.egg-info/dependency_links.txt
stancache.egg-info/requires.txt
stancache.egg-info/top_level.txt