Metadata-Version: 1.1
Name: stancache
Version: 0.1.64
Summary: Filecache for stan models
Home-page: https://github.com/jburos/stancache
Author: Jacqueline Buros Novik
Author-email: jackinovik@gmail.com
License: http://www.apache.org/licenses/LICENSE-2.0.html
Download-URL: https://github.com/jburos/stancache/tarball/0.1.64
Platform: UNKNOWN
Classifier: Development Status :: 3 - Alpha
Classifier: Environment :: Console
Classifier: Operating System :: OS Independent
Classifier: Intended Audience :: Science/Research
Classifier: License :: OSI Approved :: Apache Software License
Classifier: Programming Language :: Python
Classifier: Topic :: Scientific/Engineering :: Bio-Informatics
